sha_learning/__init__.py
sha_learning/autotwin_learn.py
sha_learning/case_studies/__init__.py
sha_learning/case_studies/auto_twin/__init__.py
sha_learning/case_studies/auto_twin/sul_definition.py
sha_learning/case_studies/auto_twin/sul_functions.py
sha_learning/case_studies/energy/__init__.py
sha_learning/case_studies/energy/sul_definition.py
sha_learning/case_studies/energy/sul_functions.py
sha_learning/case_studies/energy_made/__init__.py
sha_learning/case_studies/energy_made/sul_definition.py
sha_learning/case_studies/energy_made/sul_functions.py
sha_learning/case_studies/energy_sim/__init__.py
sha_learning/case_studies/energy_sim/sul_definition.py
sha_learning/case_studies/energy_sim/sul_functions.py
sha_learning/case_studies/hri/__init__.py
sha_learning/case_studies/hri/sul_definition.py
sha_learning/case_studies/hri/sul_functions.py
sha_learning/case_studies/thermostat/__init__.py
sha_learning/case_studies/thermostat/sul_definition.py
sha_learning/case_studies/thermostat/sul_functions.py
sha_learning/cleanup_traces.py
sha_learning/domain/__init__.py
sha_learning/domain/lshafeatures.py
sha_learning/domain/obstable.py
sha_learning/domain/shafeatures.py
sha_learning/domain/sigfeatures.py
sha_learning/domain/sulfeatures.py
sha_learning/learn_model.py
sha_learning/learning_setup/__init__.py
sha_learning/learning_setup/fastddtw.py
sha_learning/learning_setup/learner.py
sha_learning/learning_setup/logger.py
sha_learning/learning_setup/teacher.py
sha_learning/learning_setup/trace_gen.py
sha_learning/pltr/__init__.py
sha_learning/pltr/energy_made_pltr.py
sha_learning/pltr/energy_pltr.py
sha_learning/pltr/hri_pltr.py
sha_learning/pltr/lsha_report.py
sha_learning/pltr/sha_pltr.py
sha_learning/resources/config/config.ini
sha_learning/resources/learned_sha/AUTO_TWIN_SKG_100
sha_learning/resources/learned_sha/AUTO_TWIN_SKG_100.pdf
sha_learning/resources/learned_sha/AUTO_TWIN_SKG_100.txt
sha_learning/resources/learned_sha/AUTO_TWIN_SKG_100_source.txt
lsha-0.1.10.dist-info/METADATA
lsha-0.1.10.dist-info/WHEEL
lsha-0.1.10.dist-info/RECORD
