Metadata-Version: 2.3
Name: lsha
Version: 0.1.10
Summary: Automata Learning Algorithm for Stochastic Hybrid Automata
Author: livialestingi
Author-email: livia.lestingi@polimi.it
Requires-Python: >=3.10,<4.0
Classifier: Programming Language :: Python :: 3
Classifier: Programming Language :: Python :: 3.10
Classifier: Programming Language :: Python :: 3.11
Classifier: Programming Language :: Python :: 3.12
Classifier: Programming Language :: Python :: 3.13
Requires-Dist: graphviz (>=0.20.1,<0.21.0)
Requires-Dist: matplotlib (>=3.8.3,<4.0.0)
Requires-Dist: neo4j (>=5.17.0,<6.0.0)
Requires-Dist: pandas (>=2.2.1,<3.0.0)
Requires-Dist: pygad (>=3.3.1,<4.0.0)
Requires-Dist: pygraphviz (>=1.12,<2.0)
Requires-Dist: scipy (>=1.12.0,<2.0.0)
Requires-Dist: skg-connector (>=0.1.13,<0.2.0)
Requires-Dist: tqdm (>=4.66.2,<5.0.0)
